pykindler/__init__.py
pykindler/cli.py
pykindler/constants.py
pykindler/convertor.py
pykindler/utils/__init__.py
pykindler/utils/bash_utils.py
pykindler/utils/convert_utils.py
pykindler/utils/cron_utils.py
pykindler/utils/email_utils.py
pykindler/utils/nlp_utils.py
pykindler/utils/os_utils.py
pykindler-0.3.2.dist-info/LICENSE
pykindler-0.3.2.dist-info/METADATA
pykindler-0.3.2.dist-info/WHEEL
pykindler-0.3.2.dist-info/entry_points.txt
pykindler-0.3.2.dist-info/top_level.txt
pykindler-0.3.2.dist-info/RECORD
