Metadata-Version: 2.1
Name: pykindler
Version: 0.3.2
Summary: Schedules conversion of e-books to mobi, mails it to your kindle
Home-page: https://github.com/VivekBits2210/pykindler
Author: Vivek Nayak
Author-email: viveknayak2210@gmail.com
License: MIT
Platform: UNKNOWN
Classifier: Development Status :: 4 - Beta
Classifier: Programming Language :: Python :: 3.6
Classifier: Programming Language :: Python :: 3.7
Classifier: Programming Language :: Python :: 3.8
Classifier: Programming Language :: Python :: 3.9
Classifier: Intended Audience :: End Users/Desktop
Classifier: Environment :: Console
Classifier: Natural Language :: English
Classifier: Operating System :: POSIX :: Linux
Classifier: License :: OSI Approved :: MIT License
Classifier: Topic :: Utilities
Requires-Dist: black (==21.6b0)
Requires-Dist: cffi (==1.14.5)
Requires-Dist: click (==8.0.1)
Requires-Dist: cryptography (==3.4.7)
Requires-Dist: importlib-metadata (==4.6.1)
Requires-Dist: jeepney (==0.6.0)
Requires-Dist: keyring (==23.0.1)
Requires-Dist: mypy-extensions (==0.4.3)
Requires-Dist: pathspec (==0.8.1)
Requires-Dist: pgi (==0.0.11.2)
Requires-Dist: pycparser (==2.20)
Requires-Dist: pyenchant (==3.2.1)
Requires-Dist: python-crontab (==2.5.1)
Requires-Dist: python-dateutil (==2.8.1)
Requires-Dist: regex (==2021.7.1)
Requires-Dist: SecretStorage (==3.3.1)
Requires-Dist: six (==1.16.0)
Requires-Dist: toml (==0.10.2)
Requires-Dist: zipp (==3.5.0)
Requires-Dist: m2r
